djangoldp_fcpe/__init__.py
djangoldp_fcpe/models.py
djangoldp_fcpe/migrations/0001_initial.py
djangoldp_fcpe/migrations/0002_auto_20220207_1701.py
djangoldp_fcpe/migrations/__init__.py
djangoldp_fcpe-0.1.1.dist-info/METADATA
djangoldp_fcpe-0.1.1.dist-info/WHEEL
djangoldp_fcpe-0.1.1.dist-info/top_level.txt
djangoldp_fcpe-0.1.1.dist-info/RECORD
