Metadata-Version: 2.1
Name: djangoldp-fcpe
Version: 0.1.1
Summary: djangoldp package for FCPE application data
Home-page: https://git.startinblox.com/djangoldp-packages/djangoldp-fcpe
Author: StartinBlox
Author-email: calum@startinblox.com
License: UNKNOWN
Platform: UNKNOWN
Requires-Dist: djangoldp (>=2.1)
Requires-Dist: djangoldp-circle (>=2.1)
